datafarmclient/__init__.py
datafarmclient/base.py
datafarmclient/exceptions.py
datafarmclient/schemas.py
datafarmclient/utils.py
datafarmclient/entities/__init__.py
datafarmclient/entities/_entities.py
datafarmclient/timeseries/__init__.py
datafarmclient/timeseries/_timeseries.py
datafarmclient/variables/__init__.py
datafarmclient/variables/_variables.py
datafarmclient-0.0.3.dist-info/METADATA
datafarmclient-0.0.3.dist-info/WHEEL
datafarmclient-0.0.3.dist-info/licenses/LICENSE
datafarmclient-0.0.3.dist-info/RECORD
