Metadata-Version: 2.4
Name: datafarmclient
Version: 0.0.3
Summary: A python client library for accessing DataFarm
Project-URL: Homepage, https://github.com/DHI/datafarmclient
Project-URL: Bug Tracker, https://github.com/DHI/datafarmclient/issues
Author-email: William Heyman Krill <wihk@dhigroup.com>, Christian Fischer Holm <cfh@dhigroup.com>, Casper Helms <cahe@dhigroup.com>
License-File: LICENSE
Classifier: Development Status :: 2 - Pre-Alpha
Classifier: License :: OSI Approved :: MIT License
Classifier: Operating System :: OS Independent
Classifier: Programming Language :: Python :: 3
Classifier: Topic :: Scientific/Engineering
Requires-Python: >=3.10
Requires-Dist: numpy==2.1.2
Requires-Dist: pandas
Requires-Dist: pandera
Requires-Dist: python-dotenv
Requires-Dist: requests
Provides-Extra: dev
Requires-Dist: mkdocs; extra == 'dev'
Requires-Dist: mkdocs-material; extra == 'dev'
Requires-Dist: mkdocstrings[python]; extra == 'dev'
Requires-Dist: pytest; extra == 'dev'
Requires-Dist: pytest-cov; extra == 'dev'
Requires-Dist: python-dotenv; extra == 'dev'
Requires-Dist: ruff; extra == 'dev'
Provides-Extra: test
Requires-Dist: pytest; extra == 'test'
Requires-Dist: pytest-cov; extra == 'test'
Requires-Dist: python-dotenv; extra == 'test'
